QPT_SDK/__init__.py
QPT_SDK/QVCRedist/__init__.py
QPT_SDK/QVCRedist/vcredist/concrt140.dll
QPT_SDK/QVCRedist/vcredist/msvcp140.dll
QPT_SDK/QVCRedist/vcredist/msvcp140_1.dll
QPT_SDK/QVCRedist/vcredist/msvcp140_2.dll
QPT_SDK/QVCRedist/vcredist/msvcp140_atomic_wait.dll
QPT_SDK/QVCRedist/vcredist/msvcp140_codecvt_ids.dll
QPT_SDK/QVCRedist/vcredist/vcamp140.dll
QPT_SDK/QVCRedist/vcredist/vccorlib140.dll
QPT_SDK/QVCRedist/vcredist/vcomp140.dll
QVCRedist-1.0.3.dist-info/METADATA
QVCRedist-1.0.3.dist-info/WHEEL
QVCRedist-1.0.3.dist-info/top_level.txt
QVCRedist-1.0.3.dist-info/RECORD
