Metadata-Version: 2.1
Name: QVCRedist
Version: 1.0.3
Summary: QPT-Python环境打包工具 SDK
Home-page: https://github.com/GT-ZhangAcer/QPT
Author: GT-ZhangAcer
Author-email: zhangacer@foxmail.com
License: MIT
Requires-Python: >=3.8
